Metadata-Version: 2.1
Name: idact-gui
Version: 0.4.1
Summary: A small example package
Home-page: https://github.com/intdata-bsc/idact-gui
Author: Joanna Chyży, Karolina Piekarz, Piotr Swędrak
Author-email: piotrekswedrak@gmail.com
License: UNKNOWN
Platform: UNKNOWN
Classifier: Programming Language :: Python :: 3
Classifier: License :: OSI Approved :: MIT License
Requires-Dist: PyQt5 (<5.10)
